<?xml version="1.0"?>
<hibernate-mapping xmlns="urn:nhibernate-mapping-2.2"
assembly="RentStuff.Property.Domain.Model" namespace="RentStuff.Property.Domain.Model.HouseAggregate">
  <class name="Dimension" table="dimension" lazy="false">
    <id name="Id">
      <column name="id"/>
      <generator class="assigned" />
    </id>
    <property name="DimensionType" column="dimension_type"/>
    <property name="StringValue" column="string_value"/>
    <property name="DecimalValue" column="decimal_value"/>
  </class>
</hibernate-mapping>